ctddocumentation/__init__.py
ctddocumentation/api_helper.py
ctddocumentation/configuration.py
ctddocumentation/ctddocumentation_client.py
ctddocumentation/controllers/__init__.py
ctddocumentation/controllers/activities_controller.py
ctddocumentation/controllers/alerts_controller.py
ctddocumentation/controllers/assets_controller.py
ctddocumentation/controllers/base_controller.py
ctddocumentation/controllers/custom_attributes_categories_controller.py
ctddocumentation/controllers/events_controller.py
ctddocumentation/controllers/groups_controller.py
ctddocumentation/controllers/insights_controller.py
ctddocumentation/controllers/license_controller.py
ctddocumentation/controllers/login_controller.py
ctddocumentation/controllers/queries_controller.py
ctddocumentation/controllers/sensors_controller.py
ctddocumentation/controllers/sites_controller.py
ctddocumentation/controllers/tasks_controller.py
ctddocumentation/controllers/tasks_queries_controller.py
ctddocumentation/controllers/users_controller.py
ctddocumentation/exceptions/__init__.py
ctddocumentation/exceptions/api_exception.py
ctddocumentation/exceptions/auth_authenticate_401_error_exception.py
ctddocumentation/http/__init__.py
ctddocumentation/http/http_call_back.py
ctddocumentation/http/http_method_enum.py
ctddocumentation/http/http_request.py
ctddocumentation/http/http_response.py
ctddocumentation/http/auth/__init__.py
ctddocumentation/http/auth/custom_header_authentication.py
ctddocumentation/models/__init__.py
ctddocumentation/models/actionable.py
ctddocumentation/models/actionable_asset.py
ctddocumentation/models/actionable_cap.py
ctddocumentation/models/actionable_information.py
ctddocumentation/models/actionable_policy.py
ctddocumentation/models/actionable_related_asset.py
ctddocumentation/models/active_history.py
ctddocumentation/models/activities_object.py
ctddocumentation/models/activities_response.py
ctddocumentation/models/activity.py
ctddocumentation/models/add_license_response.py
n_profile_sdk-2.3.4.dist-info/LICENSE
n_profile_sdk-2.3.4.dist-info/METADATA
n_profile_sdk-2.3.4.dist-info/WHEEL
n_profile_sdk-2.3.4.dist-info/top_level.txt
n_profile_sdk-2.3.4.dist-info/RECORD
